Metadata-Version: 1.0
Name: seaborn-command
Version: 0.0.1
Summary: seaborn command line tool
Home-page: https://github.com/kojix2/seaborn-command
Author: kojix2
Author-email: 2xijok@gmail.com
License: MIT License
